<annotation>
	<folder></folder>
	<filename>adidas_0_00149_jpg.rf.fe932107b3e747cba19eedf8c0abe5ee.jpg</filename>
	<path>adidas_0_00149_jpg.rf.fe932107b3e747cba19eedf8c0abe5ee.jpg</path>
	<source>
		<database>roboflow.ai</database>
	</source>
	<size>
		<width>480</width>
		<height>360</height>
		<depth>3</depth>
	</size>
	<segmented>0</segmented>
	<object>
		<name>addidas</name>
		<pose>Unspecified</pose>
		<truncated>0</truncated>
		<difficult>0</difficult>
		<occluded>0</occluded>
		<bndbox>
			<xmin>262</xmin>
			<xmax>313</xmax>
			<ymin>80</ymin>
			<ymax>117</ymax>
		</bndbox>
	</object>
	<object>
		<name>addidas</name>
		<pose>Unspecified</pose>
		<truncated>0</truncated>
		<difficult>0</difficult>
		<occluded>0</occluded>
		<bndbox>
			<xmin>380</xmin>
			<xmax>437</xmax>
			<ymin>92</ymin>
			<ymax>129</ymax>
		</bndbox>
	</object>
</annotation>
