<annotation>
	<folder></folder>
	<filename>nike13_jpg.rf.7a32aab2d5d16a2bda38a612df683fbe.jpg</filename>
	<path>nike13_jpg.rf.7a32aab2d5d16a2bda38a612df683fbe.jpg</path>
	<source>
		<database>roboflow.ai</database>
	</source>
	<size>
		<width>480</width>
		<height>360</height>
		<depth>3</depth>
	</size>
	<segmented>0</segmented>
	<object>
		<name>nike</name>
		<pose>Unspecified</pose>
		<truncated>0</truncated>
		<difficult>0</difficult>
		<occluded>0</occluded>
		<bndbox>
			<xmin>246</xmin>
			<xmax>274</xmax>
			<ymin>100</ymin>
			<ymax>151</ymax>
		</bndbox>
	</object>
</annotation>
